latency_lens/__init__.py
latency_lens/cli.py
latency_lens/io/__init__.py
latency_lens/io/csv_reader.py
latency_lens/io/json_reader.py
latency_lens/io/normalize.py
latency_lens/report/__init__.py
latency_lens/report/html.py
latency_lens/stats/__init__.py
latency_lens/stats/jitter.py
latency_lens/stats/percentiles.py
latency_lens/stats/spikes.py
latency_lens/stats/windows.py
latency_lens-1.0.2.dist-info/licenses/LICENSE
latency_lens-1.0.2.dist-info/METADATA
latency_lens-1.0.2.dist-info/WHEEL
latency_lens-1.0.2.dist-info/entry_points.txt
latency_lens-1.0.2.dist-info/top_level.txt
latency_lens-1.0.2.dist-info/RECORD
