Metadata-Version: 2.4
Name: latency-lens
Version: 1.0.2
Summary: See p99 latency and jitter — not averages.
Author: Kinan Nasri
License: MIT
Project-URL: Homepage, https://github.com/KinanNasri/latency-lens
Project-URL: Repository, https://github.com/KinanNasri/latency-lens
Project-URL: Issues, https://github.com/KinanNasri/latency-lens/issues
Project-URL: Changelog, https://github.com/KinanNasri/latency-lens/releases
Keywords: latency,jitter,performance,profiling,observability,benchmarking,cli,percentiles,chrome-trace
Classifier: Development Status :: 4 - Beta
Classifier: Intended Audience :: Developers
Classifier: License :: OSI Approved :: MIT License
Classifier: Operating System :: OS Independent
Classifier: Programming Language :: Python :: 3
Classifier: Programming Language :: Python :: 3 :: Only
Classifier: Programming Language :: Python :: 3.11
Classifier: Programming Language :: Python :: 3.12
Classifier: Programming Language :: Python :: 3.13
Classifier: Topic :: Software Development :: Testing
Classifier: Topic :: Software Development :: Quality Assurance
Classifier: Topic :: System :: Monitoring
Classifier: Topic :: Utilities
Requires-Python: >=3.11
License-File: LICENSE
Requires-Dist: click>=8.1
Requires-Dist: rich>=13.7
Dynamic: license-file
